zfpy.cpython-310-x86_64-linux-gnu.so
zfpy.libs/libgomp-e985bcbb.so.1.0.0
zfpy.libs/libzfp-51ef9dc1.so.1
zfpy-1.0.1.dist-info/METADATA
zfpy-1.0.1.dist-info/WHEEL
zfpy-1.0.1.dist-info/top_level.txt
zfpy-1.0.1.dist-info/RECORD
zfpy-1.0.1.dist-info/licenses/LICENSE
zfpy-1.0.1.dist-info/licenses/NOTICE
