Metadata-Version: 2.1
Name: zfpy
Version: 1.0.1
Summary: zfp compression in Python
Home-page: https://zfp.llnl.gov
Author: Peter Lindstrom, Danielle Asher
Author-email: zfp@llnl.gov
License: License :: OSI Approved :: BSD License
Classifier: Intended Audience :: Developers
Classifier: Development Status :: 4 - Beta
Classifier: License :: OSI Approved :: BSD License
Classifier: Programming Language :: Python :: 3
Classifier: Programming Language :: Python :: 3.8
Classifier: Programming Language :: Python :: 3.9
Classifier: Programming Language :: Python :: 3.10
Classifier: Programming Language :: Python :: 3.11
Classifier: Programming Language :: Python :: 3.12
Classifier: Topic :: Scientific/Engineering :: Image Processing
Classifier: Topic :: System :: Archiving :: Compression
Classifier: Operating System :: POSIX
Classifier: Operating System :: MacOS
Classifier: Operating System :: Microsoft :: Windows :: Windows 10
License-File: LICENSE
License-File: NOTICE
